{
  "id": 5,
  "name": "福岡県",
  "slug": "fukuoka",
  "region": "九州",
  "averageRent": 64326,
  "latitude": 33.5904,
  "longitude": 130.4017,
  "population": 5100000,
  "description": "九州の玄関口。住みやすさNo.1との呼び声も高い。",
  "areas": [
    {
      "name": "北九州市門司区",
      "averageRent": 62067,
      "minRent": 46500,
      "maxRent": 77700,
      "latitude": 35.6762,
      "longitude": 139.6503,
      "nearestStation": "最寄駅",
      "distanceToStation": 10,
      "description": "「門司港レトロ」地区は、大正ロマン漂う歴史的建造物が並ぶ人気の観光地。関門海峡を望む景色は絶景です。焼きカレーなどのグルメも有名。九州の鉄道の起点としての歴史を持ち、落ち着いた雰囲気の中で暮らせます。",
      "features": [
        "pet_friendly",
        "cost_performance",
        "child_rearing"
      ],
      "rentByRoomType": {
        "oneRoom": 46500,
        "oneLDK": 62000,
        "twoLDK": 77700,
        "threeLDK": null
      }
    },
    {
      "name": "北九州市若松区",
      "averageRent": 60375,
      "minRent": 47700,
      "maxRent": 75800,
      "latitude": 35.6762,
      "longitude": 139.6503,
      "nearestStation": "最寄駅",
      "distanceToStation": 10,
      "description": "洞海湾に面した港湾工業地帯と、響灘に面したビーチが共存。筑豊電鉄や若戸大橋でアクセス。「グリーンパーク」は大規模な公園で、カンガルーにも会えます。風力発電所など環境エネルギー産業も盛ん。海辺の開放的な暮らしが魅力です。",
      "features": [
        "cost_performance",
        "child_rearing",
        "pet_friendly"
      ],
      "rentByRoomType": {
        "oneRoom": 47700,
        "oneLDK": 55700,
        "twoLDK": 62300,
        "threeLDK": 75800
      }
    },
    {
      "name": "北九州市戸畑区",
      "averageRent": 74225,
      "minRent": 45500,
      "maxRent": 96900,
      "latitude": 35.6762,
      "longitude": 139.6503,
      "nearestStation": "最寄駅",
      "distanceToStation": 10,
      "description": "北九州市で最も面積が小さい区ですが、コンパクトシティとして機能的。JR戸畑駅は快速・特急の一部が停車し、小倉・博多へ便利。「戸畑祇園大山笠」はユネスコ無形文化遺産。図書館や美術館が集まる文教エリアもあり、落ち着いた住環境と利便性が両立しています。",
      "features": [
        "cost_performance",
        "shopping_convenient",
        "access_good"
      ],
      "rentByRoomType": {
        "oneRoom": 45500,
        "oneLDK": 59900,
        "twoLDK": 96900,
        "threeLDK": 94600
      }
    },
    {
      "name": "北九州市小倉北区",
      "averageRent": 88100,
      "minRent": 46000,
      "maxRent": 138000,
      "latitude": 35.6762,
      "longitude": 139.6503,
      "nearestStation": "最寄駅",
      "distanceToStation": 10,
      "description": "北九州市の中心で、小倉駅には新幹線が停車します。小倉城や旦過市場、リバーウォーク北九州など、観光・商業スポットが集積。「あるあるCity」などポップカルチャーの発信地でもあります。都市機能がコンパクトにまとまった住みやすい街です。",
      "features": [
        "access_good",
        "shopping_convenient",
        "cost_performance"
      ],
      "rentByRoomType": {
        "oneRoom": 46000,
        "oneLDK": 64900,
        "twoLDK": 103500,
        "threeLDK": 138000
      }
    },
    {
      "name": "北九州市小倉南区",
      "averageRent": 59675,
      "minRent": 42300,
      "maxRent": 78300,
      "latitude": 35.6762,
      "longitude": 139.6503,
      "nearestStation": "最寄駅",
      "distanceToStation": 10,
      "description": "北九州市で最大の面積を誇り、都市と自然が共存。北九州モノレールで小倉駅へ直結し、通勤・通学に便利。日本三大カルスト「平尾台」や菅生の滝など自然スポットが豊富。新興住宅地も多く、ファミリー層に人気のベッドタウンです。",
      "features": [
        "child_rearing",
        "cost_performance",
        "pet_friendly"
      ],
      "rentByRoomType": {
        "oneRoom": 42300,
        "oneLDK": 55300,
        "twoLDK": 62800,
        "threeLDK": 78300
      }
    },
    {
      "name": "北九州市八幡東区",
      "averageRent": 70900,
      "minRent": 42000,
      "maxRent": 100400,
      "latitude": 35.6762,
      "longitude": 139.6503,
      "nearestStation": "最寄駅",
      "distanceToStation": 10,
      "description": "世界遺産「官営八幡製鐵所」の関連施設があるものづくりの街。「スペースLABO」や「いのちのたび博物館」など文化施設が充実。皿倉山からの夜景は「新日本三大夜景」。ショッピングモールもあり、歴史、文化、自然、買い物がバランスよく揃っています。",
      "features": [
        "shopping_convenient",
        "child_rearing",
        "cost_performance"
      ],
      "rentByRoomType": {
        "oneRoom": 42000,
        "oneLDK": 70300,
        "twoLDK": 100400,
        "threeLDK": null
      }
    },
    {
      "name": "北九州市八幡西区",
      "averageRent": 67600,
      "minRent": 45600,
      "maxRent": 88600,
      "latitude": 35.6762,
      "longitude": 139.6503,
      "nearestStation": "最寄駅",
      "distanceToStation": 10,
      "description": "黒崎駅を中心とした副都心エリアと、折尾などの学園都市エリアがあります。JR鹿児島本線や筑豊電鉄が利用可能。住宅地が多く、ベッドタウンとして機能しています。コストコ北九州倉庫店もあり、買い物環境も充実しています。",
      "features": [
        "child_rearing",
        "shopping_convenient",
        "access_good"
      ],
      "rentByRoomType": {
        "oneRoom": 45600,
        "oneLDK": 62100,
        "twoLDK": 74100,
        "threeLDK": 88600
      }
    },
    {
      "name": "福岡市東区",
      "averageRent": 86700,
      "minRent": 52900,
      "maxRent": 118700,
      "latitude": 35.6762,
      "longitude": 139.6503,
      "nearestStation": "最寄駅",
      "distanceToStation": 10,
      "description": "「海の中道海浜公園」や「マリンワールド海の中道」があり、レジャー環境が抜群。香椎・千早エリアは再開発でタワーマンションや商業施設が整備され、近代的な街並みに。JRと西鉄が並走しており、博多・天神へのアクセスも良好です。",
      "features": [
        "child_rearing",
        "shopping_convenient",
        "access_good"
      ],
      "rentByRoomType": {
        "oneRoom": 52900,
        "oneLDK": 72300,
        "twoLDK": 102900,
        "threeLDK": 118700
      }
    },
    {
      "name": "福岡市博多区",
      "averageRent": 119675,
      "minRent": 69400,
      "maxRent": 176700,
      "latitude": 35.6762,
      "longitude": 139.6503,
      "nearestStation": "最寄駅",
      "distanceToStation": 10,
      "description": "九州の陸の玄関口「博多駅」と空の玄関口「福岡空港」を擁する、交通とビジネスの拠点。キャナルシティ博多や中洲の屋台街など、観光スポットも満載。新幹線通勤も可能で、バリバリ働くビジネスマンに最適なエネルギッシュな街です。",
      "features": [
        "access_good",
        "shopping_convenient",
        "cost_performance"
      ],
      "rentByRoomType": {
        "oneRoom": 69400,
        "oneLDK": 90900,
        "twoLDK": 141700,
        "threeLDK": 176700
      }
    },
    {
      "name": "福岡市中央区",
      "averageRent": 151050,
      "minRent": 68600,
      "maxRent": 233800,
      "latitude": 35.6762,
      "longitude": 139.6503,
      "nearestStation": "最寄駅",
      "distanceToStation": 10,
      "description": "九州最大の繁華街「天神」や、おしゃれな店が並ぶ「大名」「薬院」があるトレンド発信地。大濠公園や舞鶴公園などの広大な緑地もあり、都会の利便性と豊かな自然環境が奇跡的に共存しています。「住みたい街」として圧倒的な人気を誇ります。",
      "features": [
        "access_good",
        "shopping_convenient",
        "safe_area"
      ],
      "rentByRoomType": {
        "oneRoom": 68600,
        "oneLDK": 107500,
        "twoLDK": 194300,
        "threeLDK": 233800
      }
    },
    {
      "name": "福岡市南区",
      "averageRent": 111925,
      "minRent": 56600,
      "maxRent": 162500,
      "latitude": 35.6762,
      "longitude": 139.6503,
      "nearestStation": "最寄駅",
      "distanceToStation": 10,
      "description": "西鉄天神大牟田線（大橋駅など）沿線に広がる住宅街。大橋駅は特急停車駅で、天神まで約5分という近さ。駅ビルがリニューアルされ、さらに便利になりました。平尾や高宮などはおしゃれなカフェやパン屋が多く、女性に人気のエリアです。",
      "features": [
        "child_rearing",
        "safe_area",
        "access_good"
      ],
      "rentByRoomType": {
        "oneRoom": 56600,
        "oneLDK": 90700,
        "twoLDK": 137900,
        "threeLDK": 162500
      }
    },
    {
      "name": "福岡市西区",
      "averageRent": 94650,
      "minRent": 52100,
      "maxRent": 133000,
      "latitude": 35.6762,
      "longitude": 139.6503,
      "nearestStation": "最寄駅",
      "distanceToStation": 10,
      "description": "「姪浜」は地下鉄空港線の始発駅で、天神・博多・空港へ座って一本でアクセス可能。「マリノアシティ福岡」などのアウトレットモールも人気。九州大学の伊都キャンパスがあり、学園都市として発展中。海も山も近く、自然環境は最高です。",
      "features": [
        "child_rearing",
        "pet_friendly",
        "shopping_convenient"
      ],
      "rentByRoomType": {
        "oneRoom": 52100,
        "oneLDK": 66600,
        "twoLDK": 133000,
        "threeLDK": 126900
      }
    },
    {
      "name": "福岡市城南区",
      "averageRent": 107475,
      "minRent": 45900,
      "maxRent": 165500,
      "latitude": 35.6762,
      "longitude": 139.6503,
      "nearestStation": "最寄駅",
      "distanceToStation": 10,
      "description": "福岡大学があり、学生が多く活気ある街。地下鉄七隈線（別府駅・七隈駅）の延伸により、博多駅へのアクセスが飛躍的に向上しました。油山などの自然も身近で、閑静な住宅街が広がっています。家賃相場も比較的リーズナブルです。",
      "features": [
        "child_rearing",
        "safe_area",
        "cost_performance"
      ],
      "rentByRoomType": {
        "oneRoom": 45900,
        "oneLDK": 82600,
        "twoLDK": 135900,
        "threeLDK": 165500
      }
    },
    {
      "name": "福岡市早良区",
      "averageRent": 142475,
      "minRent": 64700,
      "maxRent": 225800,
      "latitude": 35.6762,
      "longitude": 139.6503,
      "nearestStation": "最寄駅",
      "distanceToStation": 10,
      "description": "「西新」は商店街が活気にあふれ、文教地区としても有名で修猷館高校などがあります。「福岡タワー」や「福岡PayPayドーム」がある百道浜エリアは、近未来的な景観とビーチが広がる人気のウォーターフロント。多様な魅力を持つ区です。",
      "features": [
        "safe_area",
        "child_rearing",
        "access_good"
      ],
      "rentByRoomType": {
        "oneRoom": 64700,
        "oneLDK": 104000,
        "twoLDK": 175400,
        "threeLDK": 225800
      }
    },
    {
      "name": "大牟田市",
      "averageRent": 55925,
      "minRent": 47300,
      "maxRent": 75800,
      "latitude": 35.6762,
      "longitude": 139.6503,
      "nearestStation": "最寄駅",
      "distanceToStation": 10,
      "description": "かつての炭鉱の街で、世界遺産の宮原坑などがあります。西鉄とJRが乗り入れる大牟田駅が中心。「大牟田動物園」は動物福祉の取り組みで全国的に注目されています。独自の食文化や祭りがあり、地元愛の強い街です。",
      "features": [
        "cost_performance",
        "child_rearing",
        "pet_friendly"
      ],
      "rentByRoomType": {
        "oneRoom": 47300,
        "oneLDK": 48000,
        "twoLDK": 52600,
        "threeLDK": 75800
      }
    },
    {
      "name": "久留米市",
      "averageRent": 61925,
      "minRent": 43300,
      "maxRent": 81400,
      "latitude": 35.6762,
      "longitude": 139.6503,
      "nearestStation": "最寄駅",
      "distanceToStation": 10,
      "description": "福岡県第三の都市で、JR久留米駅には新幹線が停車します。ゴム産業の街として発展し、ブリヂストンの創業地。ラーメンや焼き鳥などのB級グルメが豊富で、食のレベルが高い街です。筑後川が流れ、医療機関も多いため、安心して暮らせます。",
      "features": [
        "access_good",
        "shopping_convenient",
        "cost_performance"
      ],
      "rentByRoomType": {
        "oneRoom": 43300,
        "oneLDK": 58900,
        "twoLDK": 64100,
        "threeLDK": 81400
      }
    },
    {
      "name": "直方市",
      "averageRent": 50033,
      "minRent": 44700,
      "maxRent": 54600,
      "latitude": 35.6762,
      "longitude": 139.6503,
      "nearestStation": "最寄駅",
      "distanceToStation": 10,
      "description": "遠賀川が流れる筑豊の中心都市。JR・平成筑豊鉄道・筑豊電鉄が乗り入れ、北九州方面へのアクセスが良好。春には河川敷にチューリップが咲き誇ります。イオンモール直方があり、買い物も便利。のどかな環境と都市への近さが魅力の街です。",
      "features": [
        "cost_performance",
        "child_rearing",
        "pet_friendly"
      ],
      "rentByRoomType": {
        "oneRoom": 44700,
        "oneLDK": 50800,
        "twoLDK": 54600,
        "threeLDK": null
      }
    },
    {
      "name": "飯塚市",
      "averageRent": 57900,
      "minRent": 46900,
      "maxRent": 69700,
      "latitude": 35.6762,
      "longitude": 139.6503,
      "nearestStation": "最寄駅",
      "distanceToStation": 10,
      "description": "筑豊地方の中心都市。「シュガーロード」の経由地で、ひよ子本舗吉野堂など有名菓子店発祥の地。近畿大学産業理工学部などのキャンパスがあり、学生も多いです。家賃相場が安く、自然に囲まれたのんびりとした生活が送れます。",
      "features": [
        "cost_performance",
        "child_rearing",
        "pet_friendly"
      ],
      "rentByRoomType": {
        "oneRoom": 46900,
        "oneLDK": 57100,
        "twoLDK": 69700,
        "threeLDK": null
      }
    },
    {
      "name": "田川市",
      "averageRent": 57500,
      "minRent": 51100,
      "maxRent": 63900,
      "latitude": 35.6762,
      "longitude": 139.6503,
      "nearestStation": "最寄駅",
      "distanceToStation": 10,
      "description": "炭鉱節発祥の地であり、ユネスコ記憶遺産の山本作兵衛の炭鉱画で知られます。ランドマークの「二本煙突」や「伊田竪坑櫓」ライトアップは幻想的。「田川ホルモン鍋」などのソウルフードも魅力。物価や家賃が安く、個性的な魅力を持つ街です。",
      "features": [
        "cost_performance",
        "pet_friendly",
        "child_rearing"
      ],
      "rentByRoomType": {
        "oneRoom": 51100,
        "oneLDK": null,
        "twoLDK": 63900,
        "threeLDK": null
      }
    },
    {
      "name": "柳川市",
      "averageRent": 46833,
      "minRent": 41000,
      "maxRent": 50800,
      "latitude": 35.6762,
      "longitude": 139.6503,
      "nearestStation": "最寄駅",
      "distanceToStation": 10,
      "description": "「川下り」で有名な水郷の街。掘割が巡る美しい景観は必見です。北原白秋の生誕地でもあります。西鉄天神大牟田線（西鉄柳川駅）が利用可能。うなぎのせいろ蒸しは絶品。観光地の賑わいと、水辺の静けさが共存しています。",
      "features": [
        "pet_friendly",
        "cost_performance",
        "child_rearing"
      ],
      "rentByRoomType": {
        "oneRoom": 41000,
        "oneLDK": 48700,
        "twoLDK": 50800,
        "threeLDK": null
      }
    },
    {
      "name": "八女市",
      "averageRent": 0,
      "minRent": 0,
      "maxRent": 0,
      "latitude": 35.6762,
      "longitude": 139.6503,
      "nearestStation": "最寄駅",
      "distanceToStation": 10,
      "description": "最高級玉露「八女茶」の産地として名高い、歴史と文化の街。白壁の町並み保存地区にはカフェや雑貨店が増え、観光客で賑わいます。伝統工芸の仏壇や提灯も有名。豊かな自然と、情緒ある古い町並みの中で、スローライフを楽しみたい人に最適です。",
      "features": [
        "pet_friendly",
        "cost_performance",
        "child_rearing"
      ],
      "rentByRoomType": {
        "oneRoom": null,
        "oneLDK": null,
        "twoLDK": null,
        "threeLDK": null
      }
    },
    {
      "name": "筑後市",
      "averageRent": 50133,
      "minRent": 45600,
      "maxRent": 55600,
      "latitude": 35.6762,
      "longitude": 139.6503,
      "nearestStation": "最寄駅",
      "distanceToStation": 10,
      "description": "九州新幹線「筑後船小屋駅」があり、博多や鹿児島へのアクセスが可能。プロ野球ソフトバンクホークスのファーム本拠地「タマホームスタジアム筑後」があり、スポーツが身近。県営筑後広域公園などの大規模公園も整備され、活気ある田園都市です。",
      "features": [
        "access_good",
        "child_rearing",
        "cost_performance"
      ],
      "rentByRoomType": {
        "oneRoom": 49200,
        "oneLDK": 45600,
        "twoLDK": 55600,
        "threeLDK": null
      }
    },
    {
      "name": "大川市",
      "averageRent": 0,
      "minRent": 0,
      "maxRent": 0,
      "latitude": 35.6762,
      "longitude": 139.6503,
      "nearestStation": "最寄駅",
      "distanceToStation": 10,
      "description": "約480年の歴史を持つ日本一の家具産地。職人の技が息づき、インテリアにこだわる人にはたまらない街です。筑後川下流の平坦な地形で、昇開橋は重要文化財かつ映えスポット。新鮮な魚介類や海苔も美味しく、食も充実しています。",
      "features": [
        "cost_performance",
        "pet_friendly",
        "child_rearing"
      ],
      "rentByRoomType": {
        "oneRoom": null,
        "oneLDK": null,
        "twoLDK": null,
        "threeLDK": null
      }
    },
    {
      "name": "行橋市",
      "averageRent": 68600,
      "minRent": 59000,
      "maxRent": 82900,
      "latitude": 35.6762,
      "longitude": 139.6503,
      "nearestStation": "最寄駅",
      "distanceToStation": 10,
      "description": "北九州市のベッドタウンとして発展。JR日豊本線（行橋駅）は特急停車駅で、小倉や博多へアクセス可能。東九州自動車道の開通でさらに便利になりました。周防灘に面し、カキなどの海産物も豊富。住みよさランキングでも評価が高い街です。",
      "features": [
        "access_good",
        "shopping_convenient",
        "cost_performance"
      ],
      "rentByRoomType": {
        "oneRoom": 59000,
        "oneLDK": 61800,
        "twoLDK": 70700,
        "threeLDK": 82900
      }
    },
    {
      "name": "豊前市",
      "averageRent": 0,
      "minRent": 0,
      "maxRent": 0,
      "latitude": 35.6762,
      "longitude": 139.6503,
      "nearestStation": "最寄駅",
      "distanceToStation": 10,
      "description": "福岡県の東端に位置し、大分県との県境。「豊前神楽」は国の重要無形民俗文化財。周防灘の「豊前海一粒かき」やカニは絶品。求菩提山や次郎坊天狗の伝説など修験道の歴史も。海と山の恵みを享受しながら、静かに暮らせるエリアです。",
      "features": [
        "cost_performance",
        "pet_friendly",
        "child_rearing"
      ],
      "rentByRoomType": {
        "oneRoom": null,
        "oneLDK": null,
        "twoLDK": null,
        "threeLDK": null
      }
    },
    {
      "name": "中間市",
      "averageRent": 51775,
      "minRent": 39900,
      "maxRent": 60500,
      "latitude": 35.6762,
      "longitude": 139.6503,
      "nearestStation": "最寄駅",
      "distanceToStation": 10,
      "description": "北九州市と福岡市の両方にアクセスしやすいベッドタウン。世界遺産「遠賀川水源地ポンプ室」があります。遠賀川河川敷は季節の花々が美しく、市民の憩いの場。スーパーや病院がコンパクトにまとまっており、車がなくても比較的暮らしやすい街です。",
      "features": [
        "access_good",
        "cost_performance",
        "child_rearing"
      ],
      "rentByRoomType": {
        "oneRoom": 39900,
        "oneLDK": 51400,
        "twoLDK": 55300,
        "threeLDK": 60500
      }
    },
    {
      "name": "小郡市",
      "averageRent": 58275,
      "minRent": 39700,
      "maxRent": 70800,
      "latitude": 35.6762,
      "longitude": 139.6503,
      "nearestStation": "最寄駅",
      "distanceToStation": 10,
      "description": "交通の便が良く、福岡市の通勤圏として急速に発展。「カエル寺（如意輪寺）」は風鈴の名所で、インスタ映えスポットとして人気。西鉄電車を使えば天神まで約30分。宝満川沿いのサイクリングロードなどもあり、利便性と健康的な暮らしが叶います。",
      "features": [
        "access_good",
        "child_rearing",
        "safe_area"
      ],
      "rentByRoomType": {
        "oneRoom": 39700,
        "oneLDK": 59600,
        "twoLDK": 63000,
        "threeLDK": 70800
      }
    },
    {
      "name": "筑紫野市",
      "averageRent": 73000,
      "minRent": 52500,
      "maxRent": 87300,
      "latitude": 35.6762,
      "longitude": 139.6503,
      "nearestStation": "最寄駅",
      "distanceToStation": 10,
      "description": "二日市温泉という歴史ある温泉地があり、日常的に温泉を楽しめます。JR（二日市駅）と西鉄（紫駅・西鉄二日市駅）が利用可能。「イオンモール筑紫野」は県内最大級の規模で、休日は多くの人で賑わいます。自然と利便性のバランスが良い街です。",
      "features": [
        "access_good",
        "shopping_convenient",
        "child_rearing"
      ],
      "rentByRoomType": {
        "oneRoom": 52500,
        "oneLDK": 68600,
        "twoLDK": 87300,
        "threeLDK": 83600
      }
    },
    {
      "name": "春日市",
      "averageRent": 70933,
      "minRent": 56700,
      "maxRent": 85100,
      "latitude": 35.6762,
      "longitude": 139.6503,
      "nearestStation": "最寄駅",
      "distanceToStation": 10,
      "description": "福岡市に隣接し、日本一人口密度が高い市（東京23区を除く）として知られる人気のベッドタウン。JR（春日駅）と西鉄（春日原駅）が利用でき、天神・博多へのアクセスが抜群。「春日公園」などの大きな公園もあり、子育て環境が非常に良いです。",
      "features": [
        "child_rearing",
        "safe_area",
        "access_good"
      ],
      "rentByRoomType": {
        "oneRoom": 56700,
        "oneLDK": 71000,
        "twoLDK": 85100,
        "threeLDK": null
      }
    },
    {
      "name": "大野城市",
      "averageRent": 96350,
      "minRent": 54400,
      "maxRent": 139100,
      "latitude": 35.6762,
      "longitude": 139.6503,
      "nearestStation": "最寄駅",
      "distanceToStation": 10,
      "description": "福岡市の南に位置し、西鉄（下大利駅など）とJR（大野城駅）が並行して走る交通至便な街。九州自動車道のICもあり、車での移動も便利。まどかぴあなどの文化施設も充実。地形が細長く、どこに住んでも駅に近いのが特徴です。",
      "features": [
        "access_good",
        "child_rearing",
        "safe_area"
      ],
      "rentByRoomType": {
        "oneRoom": 54400,
        "oneLDK": 75400,
        "twoLDK": 116500,
        "threeLDK": 139100
      }
    },
    {
      "name": "宗像市",
      "averageRent": 54400,
      "minRent": 37100,
      "maxRent": 70500,
      "latitude": 35.6762,
      "longitude": 139.6503,
      "nearestStation": "最寄駅",
      "distanceToStation": 10,
      "description": "世界遺産「神宿る島」宗像・沖ノ島と関連遺産群がある歴史ある街。JR鹿児島本線（赤間駅・東郷駅）で博多・小倉の両方へアクセス可能。教育大があり、文教地区の雰囲気も。ベッドタウンとして整備されており、住環境は良好です。",
      "features": [
        "child_rearing",
        "safe_area",
        "access_good"
      ],
      "rentByRoomType": {
        "oneRoom": 37100,
        "oneLDK": 55600,
        "twoLDK": 70500,
        "threeLDK": null
      }
    },
    {
      "name": "太宰府市",
      "averageRent": 65175,
      "minRent": 42200,
      "maxRent": 89800,
      "latitude": 35.6762,
      "longitude": 139.6503,
      "nearestStation": "最寄駅",
      "distanceToStation": 10,
      "description": "「太宰府天満宮」の門前町として、年間を通して多くの参拝客が訪れます。西鉄太宰府線が利用可能。九州国立博物館もあり、歴史と文化の薫り高い街。令和ゆかりの地としても話題に。緑豊かで落ち着いた住環境です。",
      "features": [
        "safe_area",
        "child_rearing",
        "access_good"
      ],
      "rentByRoomType": {
        "oneRoom": 42200,
        "oneLDK": 59400,
        "twoLDK": 69300,
        "threeLDK": 89800
      }
    },
    {
      "name": "古賀市",
      "averageRent": 62200,
      "minRent": 44900,
      "maxRent": 77900,
      "latitude": 35.6762,
      "longitude": 139.6503,
      "nearestStation": "最寄駅",
      "distanceToStation": 10,
      "description": "博多駅までJR快速で約20分とアクセス抜群。「食のまち」として食品加工団地があり、直売所などのイベントが盛ん。古賀グリーンパークや海岸線でのレジャーも充実。子育て支援にも力を入れており、若い世代の移住が増えている注目の街です。",
      "features": [
        "access_good",
        "child_rearing",
        "cost_performance"
      ],
      "rentByRoomType": {
        "oneRoom": 44900,
        "oneLDK": 63800,
        "twoLDK": 77900,
        "threeLDK": null
      }
    },
    {
      "name": "福津市",
      "averageRent": 71125,
      "minRent": 54900,
      "maxRent": 89900,
      "latitude": 35.6762,
      "longitude": 139.6503,
      "nearestStation": "最寄駅",
      "distanceToStation": 10,
      "description": "「宮地嶽神社」の「光の道」が嵐のCMで有名になりました。福間駅周辺は区画整理が進み、新しいマンションや商業施設が増加中。イオンモール福津もあり便利。福間海岸はウインドサーフィンのメッカで、海辺の暮らしを楽しめます。",
      "features": [
        "child_rearing",
        "safe_area",
        "shopping_convenient"
      ],
      "rentByRoomType": {
        "oneRoom": 54900,
        "oneLDK": 62000,
        "twoLDK": 77700,
        "threeLDK": 89900
      }
    },
    {
      "name": "うきは市",
      "averageRent": 44967,
      "minRent": 39500,
      "maxRent": 48000,
      "latitude": 35.6762,
      "longitude": 139.6503,
      "nearestStation": "最寄駅",
      "distanceToStation": 10,
      "description": "「フルーツ王国」として、年中フルーツ狩りが楽しめます。「筑後吉井」の白壁の町並みにはおしゃれなカフェやショップが続々オープン。棚田の風景など日本の原風景が残ります。古民家リノベーションなども盛んで、感度の高い移住者に人気です。",
      "features": [
        "pet_friendly",
        "cost_performance",
        "child_rearing"
      ],
      "rentByRoomType": {
        "oneRoom": 39500,
        "oneLDK": 47400,
        "twoLDK": 48000,
        "threeLDK": null
      }
    },
    {
      "name": "宮若市",
      "averageRent": 0,
      "minRent": 0,
      "maxRent": 0,
      "latitude": 35.6762,
      "longitude": 139.6503,
      "nearestStation": "最寄駅",
      "distanceToStation": 10,
      "description": "トヨタ自動車関連企業が多く立地する工業都市で、財政が安定。「脇田温泉」や「所田温泉」があり、日常的に温泉を楽しめます。彼岸花の名所やホタルの舞う川など自然豊か。福岡市・北九州市の中間に位置し、両方面へアクセス可能です。",
      "features": [
        "cost_performance",
        "pet_friendly",
        "child_rearing"
      ],
      "rentByRoomType": {
        "oneRoom": null,
        "oneLDK": null,
        "twoLDK": null,
        "threeLDK": null
      }
    },
    {
      "name": "嘉麻市",
      "averageRent": 0,
      "minRent": 0,
      "maxRent": 0,
      "latitude": 35.6762,
      "longitude": 139.6503,
      "nearestStation": "最寄駅",
      "distanceToStation": 10,
      "description": "遠賀川の源流に位置し、水と緑が豊かな街。ボルダリング施設やカヌー体験など、アウトドアアクティビティが充実。ブランド牛「嘉穂牛」の産地。キャンプ場もあり、自然の中でアクティブに遊び、暮らしたい人におすすめのエリアです。",
      "features": [
        "cost_performance",
        "pet_friendly",
        "child_rearing"
      ],
      "rentByRoomType": {
        "oneRoom": null,
        "oneLDK": null,
        "twoLDK": null,
        "threeLDK": null
      }
    },
    {
      "name": "朝倉市",
      "averageRent": 45800,
      "minRent": 45000,
      "maxRent": 46700,
      "latitude": 35.6762,
      "longitude": 139.6503,
      "nearestStation": "最寄駅",
      "distanceToStation": 10,
      "description": "「三連水車」や「秋月城跡」など観光名所が多く、「筑前の小京都」と称されます。原鶴温泉はW美肌の湯として有名。2017年の豪雨災害からの復興が進み、新しいコミュニティも形成されています。歴史、自然、温泉のある豊かな暮らしが実現できます。",
      "features": [
        "pet_friendly",
        "cost_performance",
        "child_rearing"
      ],
      "rentByRoomType": {
        "oneRoom": 45000,
        "oneLDK": 45700,
        "twoLDK": 46700,
        "threeLDK": null
      }
    },
    {
      "name": "みやま市",
      "averageRent": 59050,
      "minRent": 55400,
      "maxRent": 62700,
      "latitude": 35.6762,
      "longitude": 139.6503,
      "nearestStation": "最寄駅",
      "distanceToStation": 10,
      "description": "セロリや高菜漬け、みかんなど農産物の宝庫。有明海に面し、干潟の風景が広がります。「清水寺本坊庭園」は国指定名勝。九州新幹線「筑後船小屋駅」にも近く便利。広大な田園風景の中で、食と自然に恵まれた穏やかな生活が送れます。",
      "features": [
        "cost_performance",
        "pet_friendly",
        "child_rearing"
      ],
      "rentByRoomType": {
        "oneRoom": null,
        "oneLDK": 55400,
        "twoLDK": 62700,
        "threeLDK": null
      }
    },
    {
      "name": "糸島市",
      "averageRent": 67475,
      "minRent": 49200,
      "maxRent": 82300,
      "latitude": 35.6762,
      "longitude": 139.6503,
      "nearestStation": "最寄駅",
      "distanceToStation": 10,
      "description": "「輝く小さな街」ランキングで世界3位に選ばれたこともある、今最も注目されるエリア。美しい海岸線にはおしゃれなカフェや工房が点在し、サーファーや移住者に大人気。福岡市内へも電車で通える距離で、ロハスな生活が実現できます。",
      "features": [
        "pet_friendly",
        "child_rearing",
        "safe_area"
      ],
      "rentByRoomType": {
        "oneRoom": 49200,
        "oneLDK": 66000,
        "twoLDK": 72400,
        "threeLDK": 82300
      }
    },
    {
      "name": "那珂川市",
      "averageRent": 71100,
      "minRent": 71100,
      "maxRent": 71100,
      "latitude": 35.6762,
      "longitude": 139.6503,
      "nearestStation": "最寄駅",
      "distanceToStation": 10,
      "description": "2018年に市制施行した新しい市。新幹線博多南線を使えば、博多駅までなんと8分・330円で行ける驚異の利便性。駅周辺は都会的ですが、南部には五ケ山ダムやキャンプ場など大自然が広がります。利便性と自然のバランスが最高の街です。",
      "features": [
        "child_rearing",
        "safe_area",
        "access_good"
      ],
      "rentByRoomType": {
        "oneRoom": null,
        "oneLDK": 71100,
        "twoLDK": null,
        "threeLDK": null
      }
    }
  ],
  "rentByRoomType": {
    "oneRoom": 48950,
    "oneLDK": 64803,
    "twoLDK": 86091,
    "threeLDK": 115514
  }
}